{
  "transactions": [
    {
      "id": 1,
      "name": "Vyplacení faktury",
      "value": 1231,
      "type": "in",
      "created": "12.3.2018",
      "currency": "CZK"
    },
    {
      "name": "NAZEV",
      "value": 324,
      "type": "out",
      "created": "8.5.2019",
      "currency": "CZK",
      "id": 16
    },
    {
      "name": "Vyplacení faktury",
      "value": 1231,
      "type": "in",
      "created": "31.12.2019",
      "currency": "CZK",
      "id": 21
    },
    {
      "name": "Název transakce",
      "value": 2423,
      "type": "in",
      "created": "6.5.2019",
      "currency": "CZK",
      "id": 28
    },
    {
      "name": "Name",
      "value": 1000,
      "type": "in",
      "created": "6.5.2019",
      "currency": "CZK",
      "id": 29
    },
    {
      "name": "UTRATA",
      "value": 1934,
      "type": "out",
      "created": "8.5.2019",
      "currency": "CZK",
      "id": 30
    },
    {
      "name": "Name",
      "value": 0,
      "type": "in",
      "created": "8.5.2019",
      "currency": "CZK",
      "id": 31
    },
    {
      "name": "Name",
      "value": 0,
      "type": "in",
      "created": "8.5.2019",
      "currency": "CZK",
      "id": 32
    },
    {
      "name": "faoiuvcx",
      "value": 123,
      "type": "out",
      "created": "8.5.2019",
      "currency": "CZK",
      "id": 33
    },
    {
      "name": "Name",
      "value": 123,
      "type": "in",
      "created": "8.5.2019",
      "currency": "CZK",
      "id": 34
    },
    {
      "name": "hsdfh",
      "value": -11,
      "type": "in",
      "created": "8.5.2019",
      "currency": "CZK",
      "id": 36
    },
    {
      "name": "qwertr",
      "value": 534,
      "type": "in",
      "created": "8.5.2019",
      "currency": "CZK",
      "id": 37
    },
    {
      "name": "qew",
      "value": 3460,
      "type": "out",
      "created": "8.5.2019",
      "currency": "CZK",
      "id": 38
    },
    {
      "name": "Vyhozený prachy",
      "value": 23423,
      "type": "in",
      "created": "8.5.2019",
      "currency": "CZK",
      "id": 39
    },
    {
      "name": "Name",
      "value": 1420,
      "type": "out",
      "created": "8.5.2019",
      "currency": "CZK",
      "id": 40
    }
  ]
}